{
  "audit_timestamp": "2026-07-12T11:29:55Z",
  "boundary_status": "POLYGON_PIP_OK",
  "boundary_method": "POLYGON_PIP",
  "source_file": "unknown",
  "total_input_clusters": 3,
  "kept": 1,
  "rejected": 2,
  "note": "Trusted polygon PiP filtering applied. Only in-boundary centroids passed.",
  "clusters": [
    {
      "cluster_id": "INSIDE",
      "primary_street": "Inside Street",
      "lat": 0.5,
      "lon": 0.5,
      "verdict": "KEPT",
      "rejection_reason": null
    },
    {
      "cluster_id": "OUTSIDE",
      "primary_street": "Outside Street",
      "lat": 2.0,
      "lon": 2.0,
      "verdict": "REJECTED",
      "rejection_reason": "OUTSIDE_NEUSS_BOUNDARY"
    },
    {
      "cluster_id": "NULL",
      "primary_street": "Null Street",
      "lat": null,
      "lon": null,
      "verdict": "REJECTED_NULL_COORDS",
      "rejection_reason": "NULL_OR_MALFORMED_COORDS"
    }
  ]
}